pyphantom/__init__.py
pyphantom/discover.py
pyphantom/flex.py
pyphantom/frame.py
pyphantom/network.py
pyphantom/structures.py
pyphantom/utils.py
pyphantom/cli/__init__.py
pyphantom/cli/pfs_cam.py
pyphantom/fakecam/__init__.py
pyphantom/fakecam/fakecam-ph7.py
pyphantom/fakecam/fakecam.png
pyphantom/fakecam/fakecam.py
pyphantom/fakecam/fakecam.spec
pyphantom/fakecam/fakecam_data.py
pyphantom/fakecam/ximg_send.py
pyphantom/fakecam/takes/0.data
pyphantom/fakecam/takes/0.raw
pyphantom/fakecam/takes/1.data
pyphantom/fakecam/takes/1.raw
pyphantom/fakecam/takes/2.data
pyphantom/fakecam/takes/2.raw
pyphantom/fakecam/takes/3.data
pyphantom/fakecam/takes/3.raw
pyphantom/fakecam/takes-ph7/0.data
pyphantom/fakecam/takes-ph7/0.raw
tests/__init__.py
tests/conftest.py
tests/test_fakecam.py
tests/test_flex.py
pyphantom-0.2.9.dist-info/LICENSE
pyphantom-0.2.9.dist-info/METADATA
pyphantom-0.2.9.dist-info/WHEEL
pyphantom-0.2.9.dist-info/entry_points.txt
pyphantom-0.2.9.dist-info/top_level.txt
pyphantom-0.2.9.dist-info/RECORD
